Metadata-Version: 2.1
Name: oqmscore
Version: 0.1
Summary: Objective quality measure score for speech
Home-page: https://github.com/rohit18115/OQMscores-python
Author: Rohit Arora
Author-email: rohit18115@iiitd.ac.in
License: UNKNOWN
Platform: UNKNOWN
License-File: LICENSE
